{
  "asia": {
    "vortex_api": ["https://vortex.worldofwarships.asia"],
    "clan_api": "https://clans.worldofwarships.asia",
    "official_api": "https://api.worldofwarships.asia"
  },
  "eu": {
    "vortex_api": ["https://vortex.worldofwarships.eu"],
    "clan_api": "https://clans.worldofwarships.eu",
    "official_api": "https://api.worldofwarships.eu"
  },
  "na": {
    "vortex_api": ["https://vortex.worldofwarships.eu"],
    "clan_api": "https://clans.worldofwarships.eu",
    "official_api": "https://api.worldofwarships.eu"
  },
  "ru": {
    "vortex_api": ["https://vortex.korabli.su"],
    "clan_api": "https://clans.korabli.su",
    "official_api": "https://api.korabli.su"
  },
  "cn": {
    "vortex_api": ["https://vortex.wowsgame.cn"],
    "clan_api": "https://clans.wowsgame.cn",
    "official_api": null
  }
}
